CHANGELOG.md
LICENSE
MANIFEST.in
README.md
__init__.py
setup.py
robocadSim/__init__.py
robocadSimPy.egg-info/PKG-INFO
robocadSimPy.egg-info/SOURCES.txt
robocadSimPy.egg-info/dependency_links.txt
robocadSimPy.egg-info/requires.txt
robocadSimPy.egg-info/top_level.txt
robocadSim/robots/RT1.py
robocadSim/robots/RT2.py
robocadSim/robots/__init__.py
robocadSim/robots/line_sensor_cls.py
robocadSim/robots/dev/__init__.py
robocadSim/robots/dev/connection.py
robocadSim/robots/dev/connection_helper.py
robocadSim/robots/dev/holder.py