Metadata-Version: 2.1
Name: robocadSimPy
Version: 0.0.6.10
Summary: python lib for robocadV
Home-page: https://robocadv.readthedocs.io/en/latest/docs/all_docs/lib_docs/python/index.html
Author: Abdrakov Airat
Author-email: abdrakovairat@gmail.com
License: MIT
Keywords: simulator,robotics,robot,3d
Platform: UNKNOWN
Classifier: Development Status :: 5 - Production/Stable
Classifier: Intended Audience :: Education
Classifier: Operating System :: Microsoft :: Windows :: Windows 10
Classifier: License :: OSI Approved :: MIT License
Classifier: Programming Language :: Python :: 3
License-File: LICENSE
